submarine/__init__.py
submarine/exceptions.py
submarine/artifacts/__init__.py
submarine/artifacts/repository.py
submarine/cli/__init__.py
submarine/cli/main.py
submarine/cli/config/__init__.py
submarine/cli/config/cli_config.yaml
submarine/cli/config/command.py
submarine/cli/config/config.py
submarine/cli/environment/__init__.py
submarine/cli/environment/command.py
submarine/cli/experiment/__init__.py
submarine/cli/experiment/command.py
submarine/cli/notebook/__init__.py
submarine/cli/notebook/command.py
submarine/cli/sandbox/__init__.py
submarine/cli/sandbox/command.py
submarine/cli/serve/__init__.py
submarine/cli/serve/command.py
submarine/client/__init__.py
submarine/client/api_client.py
submarine/client/configuration.py
submarine/client/exceptions.py
submarine/client/rest.py
submarine/client/api/__init__.py
submarine/client/api/auth_api.py
submarine/client/api/environment_api.py
submarine/client/api/environment_client.py
submarine/client/api/experiment_api.py
submarine/client/api/experiment_client.py
submarine/client/api/experiment_template_api.py
submarine/client/api/experiment_templates_api.py
submarine/client/api/model_version_api.py
submarine/client/api/notebook_api.py
submarine/client/api/notebook_client.py
submarine/client/api/registered_model_api.py
submarine/client/api/serve_api.py
submarine/client/api/serve_client.py
submarine/client/models/__init__.py
submarine/client/models/code_spec.py
submarine/client/models/environment_spec.py
submarine/client/models/experiment_meta.py
submarine/client/models/experiment_spec.py
submarine/client/models/experiment_task_spec.py
submarine/client/models/experiment_template_param_spec.py
submarine/client/models/experiment_template_spec.py
submarine/client/models/experiment_template_submit.py
submarine/client/models/git_code_spec.py
submarine/client/models/json_response.py
submarine/client/models/kernel_spec.py
submarine/client/models/login_param.py
submarine/client/models/model_version_entity.py
apache_submarine-0.8.0.dist-info/METADATA
apache_submarine-0.8.0.dist-info/WHEEL
apache_submarine-0.8.0.dist-info/entry_points.txt
apache_submarine-0.8.0.dist-info/top_level.txt
apache_submarine-0.8.0.dist-info/RECORD
