Metadata-Version: 2.1
Name: apache-submarine
Version: 0.8.0
Summary: A python SDK for submarine
Home-page: https://github.com/apache/submarine
Maintainer: Apache Submarine Community
Maintainer-email: dev@submarine.apache.org
License: Apache License, Version 2.0
Platform: UNKNOWN
Classifier: Intended Audience :: Developers
Classifier: Programming Language :: Python :: 3.7
Classifier: Programming Language :: Python :: 3.8
Classifier: Programming Language :: Python :: 3.9
Classifier: Programming Language :: Python :: 3.10
Requires-Dist: numpy
Requires-Dist: pandas
Requires-Dist: sqlalchemy (<2.0.0,>=1.4.0)
Requires-Dist: sqlparse
Requires-Dist: pymysql
Requires-Dist: requests (>=2.26.0)
Requires-Dist: urllib3 (>=1.15.1)
Requires-Dist: certifi (>=14.05.14)
Requires-Dist: python-dateutil (>=2.5.3)
Requires-Dist: pyarrow (>=6.0.1)
Requires-Dist: boto3 (>=1.17.58)
Requires-Dist: click (>=8.1.0)
Requires-Dist: rich
Requires-Dist: dacite
Requires-Dist: pyaml
Provides-Extra: pytorch
Requires-Dist: torch (>=1.5.0) ; extra == 'pytorch'
Requires-Dist: torchvision (>=0.6.0) ; extra == 'pytorch'
Provides-Extra: tf
Requires-Dist: tensorflow (==1.15.5) ; extra == 'tf'
Requires-Dist: numpy (<1.19.0,>=1.16.0) ; extra == 'tf'
Requires-Dist: protobuf (<3.20,>=3.6.1) ; extra == 'tf'
Provides-Extra: tf2
Requires-Dist: tensorflow (<2.10.0,>=2.6.0) ; extra == 'tf2'
Requires-Dist: numpy (>=1.14.5) ; extra == 'tf2'
Requires-Dist: keras (>=2.6.0) ; extra == 'tf2'
Requires-Dist: protobuf (<3.20,>=3.9.2) ; extra == 'tf2'
Requires-Dist: tensorflow-addons (==0.17.0) ; extra == 'tf2'
Requires-Dist: tensorflow-estimator (<2.10.0,>=2.6.0) ; extra == 'tf2'
Requires-Dist: tf-slim (==1.1.0) ; extra == 'tf2'
Requires-Dist: typeguard (<3.0.0) ; extra == 'tf2'
Requires-Dist: scipy (<1.11.0) ; extra == 'tf2'
